torch_composer/__init__.py
torch_composer/_nn_composer/__init__.py
torch_composer/_nn_composer/_compose_nn_sequential.py
torch_composer-0.0.3.dist-info/LICENSE
torch_composer-0.0.3.dist-info/METADATA
torch_composer-0.0.3.dist-info/WHEEL
torch_composer-0.0.3.dist-info/top_level.txt
torch_composer-0.0.3.dist-info/RECORD
