Metadata-Version: 2.1
Name: torch-composer
Version: 0.0.3
Summary: API to compose pytorch neural networks
Author: Michael E. Vinyard - Harvard University - Broad Institute of MIT and Harvard - Massachussetts General Hospital
Author-email: mvinyard@broadinstitute.org
License: MIT
Classifier: Development Status :: 2 - Pre-Alpha
Classifier: Programming Language :: Python :: 3.6
Classifier: Intended Audience :: Science/Research
Classifier: Topic :: Scientific/Engineering :: Bio-Informatics
Requires-Python: >3.6.0
License-File: LICENSE
Requires-Dist: torch (>=1.12)
